{"logo":"https://cdn.jsdelivr.net/gh/Cha-Shao/addon-station-list/ia/assets/logo_822980_94516.png","title":"RpChat NTD | 1.12 - 1.19 | Head chat ⚡ Scoreboard DM ⚡ Hoverable chat ⚡ RP commands ⚡ Oraxen support","content":"Cool revamped RpChat. Head chat, hoverable chat, scoreboard DM! Oraxen, ItemsAdder support","premium":true,"link":"https://www.spigotmc.org/resources/94516","image":"https://cdn.jsdelivr.net/gh/Cha-Shao/addon-station-list/ia/assets/image_822980_94516.png","tags":[],"time":1629196200}